IngeoML/__init__.py
IngeoML/analysis.py
IngeoML/cluster.py
IngeoML/feature_selection.py
IngeoML/jax_utils.py
IngeoML/optimizer.py
IngeoML/supervised_learning.py
IngeoML/utils.py
IngeoML/tests/__init__.py
IngeoML/tests/test_analysis.py
IngeoML/tests/test_cluster.py
IngeoML/tests/test_feature_selection.py
IngeoML/tests/test_jax_utils.py
IngeoML/tests/test_optimizer.py
IngeoML/tests/test_supervised_learning.py
IngeoML/tests/test_utils.py
IngeoML-0.0.29.dist-info/LICENSE
IngeoML-0.0.29.dist-info/METADATA
IngeoML-0.0.29.dist-info/WHEEL
IngeoML-0.0.29.dist-info/top_level.txt
IngeoML-0.0.29.dist-info/RECORD
